duravoke/__init__.py
duravoke/duravokable.py
duravoke/duravoke.py
duravoke/duravoke_context.py
duravoke/kv.py
duravoke/serializer.py
duravoke/utils/__init__.py
duravoke/utils/methods.py
duravoke-0.1.3.dist-info/METADATA
duravoke-0.1.3.dist-info/WHEEL
duravoke-0.1.3.dist-info/licenses/LICENSE
duravoke-0.1.3.dist-info/RECORD
