Metadata-Version: 2.4
Name: duravoke
Version: 0.1.3
Summary: A mini durable execution library, with an extreme focus on simplicity
Project-URL: Homepage, https://github.com/sourabhdesai/duravoke
Project-URL: Repository, https://github.com/sourabhdesai/duravoke
Author: Sourabh Desai
License-File: LICENSE
Keywords: async,durable execution,idempotency,workflow
Classifier: Development Status :: 3 - Alpha
Classifier: Intended Audience :: Developers
Classifier: Programming Language :: Python :: 3
Classifier: Programming Language :: Python :: 3.9
Classifier: Programming Language :: Python :: 3.10
Classifier: Programming Language :: Python :: 3.11
Classifier: Programming Language :: Python :: 3.12
Classifier: Programming Language :: Python :: 3.13
Requires-Python: >=3.10
